{
  "name": "Emacs",
  "description": "Standard Emacs keybindings",
  "version": "1.0.0",
  "hotkeys": [
    { "command": "test:save", "key": "ctrl+x ctrl+s" },
    { "command": "editor:delete-word", "key": "meta+d" },
    { "command": "editor:yank", "key": "ctrl+y" },
    { "command": "editor:forward-char", "key": "ctrl+f" },
    { "command": "editor:backward-char", "key": "ctrl+b" },
    { "command": "editor:next-line", "key": "ctrl+n" },
    { "command": "editor:previous-line", "key": "ctrl+p" },
    { "command": "editor:move-beginning-of-line", "key": "ctrl+a" },
    { "command": "editor:move-end-of-line", "key": "ctrl+e" },
    { "command": "editor:forward-word", "key": "meta+f" },
    { "command": "editor:backward-word", "key": "meta+b" },
    { "command": "editor:scroll-up", "key": "ctrl+v" },
    { "command": "editor:scroll-down", "key": "meta+v" },
    { "command": "editor:beginning-of-buffer", "key": "shift+meta+," },
    { "command": "editor:end-of-buffer", "key": "shift+meta+." }
  ]
}
